pytextract/__init__.py
pytextract/cli.py
pytextract/colors.py
pytextract/exceptions.py
pytextract/parsers/__init__.py
pytextract/parsers/audio.py
pytextract/parsers/csv_parser.py
pytextract/parsers/doc_parser.py
pytextract/parsers/docx_parser.py
pytextract/parsers/eml_parser.py
pytextract/parsers/epub_parser.py
pytextract/parsers/gif_parser.py
pytextract/parsers/html_parser.py
pytextract/parsers/image.py
pytextract/parsers/jpg_parser.py
pytextract/parsers/json_parser.py
pytextract/parsers/mp3_parser.py
pytextract/parsers/msg_parser.py
pytextract/parsers/odt_parser.py
pytextract/parsers/ogg_parser.py
pytextract/parsers/pdf_parser.py
pytextract/parsers/png_parser.py
pytextract/parsers/pptx_parser.py
pytextract/parsers/ps_parser.py
pytextract/parsers/psv_parser.py
pytextract/parsers/rtf_parser.py
pytextract/parsers/tiff_parser.py
pytextract/parsers/tsv_parser.py
pytextract/parsers/txt_parser.py
pytextract/parsers/utils.py
pytextract/parsers/wav_parser.py
pytextract/parsers/xls_parser.py
pytextract/parsers/xlsx_parser.py
pytextract-2.0.1.dist-info/LICENSE
pytextract-2.0.1.dist-info/METADATA
pytextract-2.0.1.dist-info/WHEEL
pytextract-2.0.1.dist-info/RECORD
