Metadata-Version: 2.1
Name: pytextract
Version: 2.0.1
Summary: 
Author: pedrovidal
Author-email: pedrovidal@escavador.com
Requires-Python: >=3.9,<4.0
Classifier: Programming Language :: Python :: 3
Classifier: Programming Language :: Python :: 3.9
Classifier: Programming Language :: Python :: 3.10
Classifier: Programming Language :: Python :: 3.11
Requires-Dist: antiword (>=0.1.0,<0.2.0)
Requires-Dist: argcomplete (>=3.1.1,<4.0.0)
Requires-Dist: beautifulsoup4 (>=4.12.2,<5.0.0)
Requires-Dist: chardet (>=5.2.0,<6.0.0)
Requires-Dist: docx2txt (>=0.8,<0.9)
Requires-Dist: extract-msg (>=0.45.0,<0.46.0)
Requires-Dist: pdfminer-six (>=20221105,<20221106)
Requires-Dist: python-pptx (>=0.6.22,<0.7.0)
Requires-Dist: six (>=1.16.0,<2.0.0)
Requires-Dist: speechrecognition (>=3.10.0,<4.0.0)
Requires-Dist: striprtf (>=0.0.26,<0.0.27)
Requires-Dist: xlrd (>=2.0.1,<3.0.0)
